openstack/__init__.py
openstack/session.py
openstack/resource.py
openstack/exceptions.py
openstack/connection.py
openstack/profile.py
openstack/format.py
openstack/module_loader.py
openstack/transport.py
openstack/proxy.py
openstack/utils.py
openstack/network/__init__.py
openstack/network/network_service.py
openstack/network/version.py
openstack/network/v2/__init__.py
openstack/network/v2/extension.py
openstack/network/v2/router.py
openstack/network/v2/metering_label.py
openstack/network/v2/subnet.py
openstack/network/v2/metering_label_rule.py
openstack/network/v2/health_monitor.py
openstack/network/v2/network.py
openstack/network/v2/load_balancer.py
openstack/network/v2/security_group_rule.py
openstack/network/v2/_proxy.py
openstack/network/v2/floating_ip.py
openstack/network/v2/quota.py
openstack/network/v2/pool_member.py
openstack/network/v2/pool.py
openstack/network/v2/port.py
openstack/network/v2/listener.py
openstack/network/v2/security_group.py
openstack/network/v2/thin.py
openstack/clustering/__init__.py
openstack/clustering/version.py
openstack/clustering/clustering_service.py
openstack/compute/__init__.py
openstack/compute/compute_service.py
openstack/compute/version.py
openstack/compute/v2/server_metadata.py
openstack/compute/v2/__init__.py
openstack/compute/v2/server_ip.py
openstack/compute/v2/extension.py
openstack/compute/v2/server_meta.py
openstack/compute/v2/flavor.py
openstack/compute/v2/_proxy.py
openstack/compute/v2/server.py
openstack/compute/v2/image.py
openstack/compute/v2/server_interface.py
openstack/compute/v2/keypair.py
openstack/compute/v2/limits.py
openstack/image/__init__.py
openstack/image/image_service.py
openstack/image/v2/__init__.py
openstack/image/v2/member.py
openstack/image/v2/_proxy.py
openstack/image/v2/image.py
openstack/image/v2/tag.py
openstack/image/v1/__init__.py
openstack/image/v1/_proxy.py
openstack/image/v1/image.py
openstack/tests/__init__.py
python_openstacksdk-0.5.0.dist-info/DESCRIPTION.rst
python_openstacksdk-0.5.0.dist-info/METADATA
python_openstacksdk-0.5.0.dist-info/WHEEL
python_openstacksdk-0.5.0.dist-info/top_level.txt
python_openstacksdk-0.5.0.dist-info/pbr.json
python_openstacksdk-0.5.0.dist-info/entry_points.txt
python_openstacksdk-0.5.0.dist-info/metadata.json
python_openstacksdk-0.5.0.dist-info/RECORD
