Metadata-Version: 2.0
Name: python-openstacksdk
Version: 0.5.0
Summary: An SDK for building applications to work with OpenStack
Home-page: http://www.openstack.org/
Author: OpenStack
Author-email: openstack-dev@lists.openstack.org
License: UNKNOWN
Platform: UNKNOWN
Classifier: Environment :: OpenStack
Classifier: Intended Audience :: Information Technology
Classifier: Intended Audience :: System Administrators
Classifier: License :: OSI Approved :: Apache Software License
Classifier: Operating System :: POSIX :: Linux
Classifier: Programming Language :: Python
Classifier: Programming Language :: Python :: 2
Classifier: Programming Language :: Python :: 2.7
Classifier: Programming Language :: Python :: 2.6
Classifier: Programming Language :: Python :: 3
Classifier: Programming Language :: Python :: 3.3
Classifier: Programming Language :: Python :: 3.4
Requires-Dist: pbr (>=0.11,<2.0)
Requires-Dist: requests (>=2.5.2)
Requires-Dist: six (>=1.9.0)
Requires-Dist: stevedore (>=1.3.0)
Requires-Dist: oslo.utils (>=1.4.0)
